decorator.py
decorator-5.0.8.dist-info/LICENSE.txt
decorator-5.0.8.dist-info/METADATA
decorator-5.0.8.dist-info/WHEEL
decorator-5.0.8.dist-info/pbr.json
decorator-5.0.8.dist-info/top_level.txt
decorator-5.0.8.dist-info/RECORD
